rpi5_wanbot_exporter/__init__.py
rpi5_wanbot_exporter/wanbot_exporter.py
rpi5_wanbot_exporter/bin/bbk_cli_linux_aarch64-1.0
rpi5_wanbot_exporter/bin/bbk_cli_linux_amd64-1.0
rpi5_wanbot_exporter/lib/__init__.py
rpi5_wanbot_exporter/lib/bbkcli_metrics.py
rpi5_wanbot_exporter/lib/ping_metrics.py
rpi5_wanbot_exporter/lib/rpi5_metrics.py
rpi5_wanbot_exporter-0.4.dist-info/LICENSE.md
rpi5_wanbot_exporter-0.4.dist-info/METADATA
rpi5_wanbot_exporter-0.4.dist-info/WHEEL
rpi5_wanbot_exporter-0.4.dist-info/entry_points.txt
rpi5_wanbot_exporter-0.4.dist-info/top_level.txt
rpi5_wanbot_exporter-0.4.dist-info/RECORD
