Metadata-Version: 2.1
Name: rpi5-wanbot-exporter
Version: 0.4
Summary: Application to check WAN connection and export metrics to Prometheus
Author-email: Niklas Melin <niklasme@pm.me>
License: MIT
Project-URL: Homepage, https://gitlab.com/wanbot
Keywords: prometheus,raspberrypi,network,exporter,rpi5
Classifier: Development Status :: 4 - Beta
Classifier: Programming Language :: Python :: 3
Classifier: License :: OSI Approved :: MIT License
Classifier: Operating System :: OS Independent
Requires-Python: >=3.11
License-File: LICENSE.md
Requires-Dist: prometheus-client
Requires-Dist: psutil
